{
  "materials": [
    {
      "item": {
        "type": "forge:partial_nbt",
        "item": "tacz:ammo",
        "nbt": {
          "AmmoId": "cyber_armorer:material_2"
        }
      },
      "count": 14
    },
    {
      "item": {
        "type": "forge:partial_nbt",
        "item": "tacz:ammo",
        "nbt": {
          "AmmoId": "cyber_armorer:material_1"
        }
      },
      "count": 6
    }
  ],
  "result": {
    "type": "attachment",
    "id": "cyber_armorer:optic_02"
  },
  "type": "tacz:gun_smith_table_crafting"
}